brailleimg/__init__.py
brailleimg/__main__.py
brailleimg/cli.py
brailleimg/conversion.py
brailleimg/dither.py
brailleimg/preprocess.py
brailleimg/util.py
brailleimg-0.2.dist-info/METADATA
brailleimg-0.2.dist-info/WHEEL
brailleimg-0.2.dist-info/entry_points.txt
brailleimg-0.2.dist-info/top_level.txt
brailleimg-0.2.dist-info/RECORD
