Metadata-Version: 2.4
Name: brailleimg
Version: 0.2
Summary: Image to braillecode converter
Author-email: Dash <dash@wind.garden>
Requires-Python: >=3.12
Requires-Dist: numpy
Requires-Dist: pillow>=11.3.0
Provides-Extra: tests
Requires-Dist: pytest; extra == "tests"
